llm_module_extension/__init__.py
llm_module_extension/interactive_dialog.py
llm_module_extension/llm_factory.py
llm_module_extension-0.1.0.dist-info/METADATA
llm_module_extension-0.1.0.dist-info/WHEEL
llm_module_extension-0.1.0.dist-info/RECORD
